odoo/addons/sale_attached_product/README.rst
odoo/addons/sale_attached_product/__init__.py
odoo/addons/sale_attached_product/__manifest__.py
odoo/addons/sale_attached_product/i18n/sale_attached_product.pot
odoo/addons/sale_attached_product/models/__init__.py
odoo/addons/sale_attached_product/models/product_template.py
odoo/addons/sale_attached_product/models/sale_attached_product_mixin.py
odoo/addons/sale_attached_product/models/sale_order.py
odoo/addons/sale_attached_product/readme/CONFIGURE.rst
odoo/addons/sale_attached_product/readme/CONTRIBUTORS.rst
odoo/addons/sale_attached_product/readme/DESCRIPTION.rst
odoo/addons/sale_attached_product/readme/USAGE.rst
odoo/addons/sale_attached_product/static/description/icon.png
odoo/addons/sale_attached_product/static/description/index.html
odoo/addons/sale_attached_product/tests/__init__.py
odoo/addons/sale_attached_product/tests/test_sale_attached_product.py
odoo/addons/sale_attached_product/views/product_template_views.xml
odoo13_addon_sale_attached_product-13.0.1.0.1.dev4.dist-info/METADATA
odoo13_addon_sale_attached_product-13.0.1.0.1.dev4.dist-info/WHEEL
odoo13_addon_sale_attached_product-13.0.1.0.1.dev4.dist-info/top_level.txt
odoo13_addon_sale_attached_product-13.0.1.0.1.dev4.dist-info/RECORD
